Training_easy_pytorch/__init__.py
Training_easy_pytorch/train_ann.py
simpleTorch/__init__.py
simpleTorch/train_ann.py
simpleTorch-0.0.3.dist-info/LICENSE
simpleTorch-0.0.3.dist-info/METADATA
simpleTorch-0.0.3.dist-info/WHEEL
simpleTorch-0.0.3.dist-info/top_level.txt
simpleTorch-0.0.3.dist-info/RECORD
