Metadata-Version: 2.1
Name: simpleTorch
Version: 0.0.3
Summary: This package is built on pytorch to avoid some standard steps
Home-page: https://github.com/panos108/Training_ANN_with_Pytorch/tree/master
Author: Panos Petsagkourakis
Author-email: p.petsagkourakis@ucl.ac.uk
License: UNKNOWN
Platform: UNKNOWN
Classifier: Programming Language :: Python :: 3
Classifier: License :: OSI Approved :: MIT License
Classifier: Operating System :: OS Independent
Requires-Python: >=3.6
